{
	"info": {
		"_postman_id": "ad6cb5ca-4ef7-41eb-b11f-d01d0a32955d",
		"name": "timeformed",
		"schema": "https://schema.getpostman.com/json/collection/v2.1.0/collection.json",
		"_exporter_id": "40273124"
	},
	"item": [
		{
			"name": "http://localhost:8080/api/timeformed/users",
			"event": [
				{
					"listen": "prerequest",
					"script": {
						"exec": [
							""
						],
						"type": "text/javascript",
						"packages": {}
					}
				}
			],
			"request": {
				"auth": {
					"type": "noauth"
				},
				"method": "POST",
				"header": [],
				"body": {
					"mode": "raw",
					"raw": "{\r\n  \"name\": \"Alejandro\",\r\n  \"email\": \"Alejandro@example.com\",\r\n  \"age\": 20\r\n}\r\n",
					"options": {
						"raw": {
							"language": "json"
						}
					}
				},
				"url": {
					"raw": "http://localhost:8080/api/timeformed/users",
					"protocol": "http",
					"host": [
						"localhost"
					],
					"port": "8080",
					"path": [
						"api",
						"timeformed",
						"users"
					]
				}
			},
			"response": []
		},
		{
			"name": "http://localhost:8080/api/timeformed/users",
			"request": {
				"auth": {
					"type": "noauth"
				},
				"method": "POST",
				"header": [],
				"body": {
					"mode": "raw",
					"raw": "{\r\n  \"name\": \"Alison Carrion\",\r\n  \"email\": \"alis2@hotmail.com\",\r\n  \"age\": 20\r\n}",
					"options": {
						"raw": {
							"language": "json"
						}
					}
				},
				"url": {
					"raw": "http://localhost:8080/api/timeformed/users",
					"protocol": "http",
					"host": [
						"localhost"
					],
					"port": "8080",
					"path": [
						"api",
						"timeformed",
						"users"
					]
				}
			},
			"response": []
		},
		{
			"name": "http://localhost:8080/api/timeformed/users/1",
			"request": {
				"auth": {
					"type": "noauth"
				},
				"method": "PUT",
				"header": [],
				"body": {
					"mode": "raw",
					"raw": "{\r\n  \"name\": \"Alejandro Barrionuevo\",\r\n  \"email\": \"Alejandrob@example.com\",\r\n  \"age\": 21\r\n}\r\n",
					"options": {
						"raw": {
							"language": "json"
						}
					}
				},
				"url": {
					"raw": "http://localhost:8080/api/timeformed/users/1",
					"protocol": "http",
					"host": [
						"localhost"
					],
					"port": "8080",
					"path": [
						"api",
						"timeformed",
						"users",
						"1"
					]
				}
			},
			"response": []
		},
		{
			"name": "http://localhost:8080/api/timeformed/users/1",
			"protocolProfileBehavior": {
				"disableBodyPruning": true
			},
			"request": {
				"auth": {
					"type": "noauth"
				},
				"method": "GET",
				"header": [],
				"body": {
					"mode": "raw",
					"raw": "\r\n"
				},
				"url": {
					"raw": "http://localhost:8080/api/timeformed/users/1",
					"protocol": "http",
					"host": [
						"localhost"
					],
					"port": "8080",
					"path": [
						"api",
						"timeformed",
						"users",
						"1"
					]
				}
			},
			"response": []
		},
		{
			"name": "http://localhost:8080/api/timeformed/users",
			"protocolProfileBehavior": {
				"disableBodyPruning": true
			},
			"request": {
				"auth": {
					"type": "noauth"
				},
				"method": "GET",
				"header": [],
				"body": {
					"mode": "raw",
					"raw": "\r\n"
				},
				"url": {
					"raw": "http://localhost:8080/api/timeformed/users",
					"protocol": "http",
					"host": [
						"localhost"
					],
					"port": "8080",
					"path": [
						"api",
						"timeformed",
						"users"
					]
				}
			},
			"response": []
		},
		{
			"name": "http://localhost:8080/api/timeformed/users/1",
			"request": {
				"auth": {
					"type": "noauth"
				},
				"method": "DELETE",
				"header": [],
				"body": {
					"mode": "raw",
					"raw": "\r\n"
				},
				"url": {
					"raw": "http://localhost:8080/api/timeformed/users/1",
					"protocol": "http",
					"host": [
						"localhost"
					],
					"port": "8080",
					"path": [
						"api",
						"timeformed",
						"users",
						"1"
					]
				}
			},
			"response": []
		},
		{
			"name": "http://localhost:8080/api/timeformed/meds",
			"request": {
				"auth": {
					"type": "noauth"
				},
				"method": "POST",
				"header": [],
				"body": {
					"mode": "raw",
					"raw": "{\r\n  \"name\": \"Omeprazol\",\r\n  \"description\": \"Antiacido y antiinflamatorio\"\r\n}\r\n",
					"options": {
						"raw": {
							"language": "json"
						}
					}
				},
				"url": {
					"raw": "http://localhost:8080/api/timeformed/meds",
					"protocol": "http",
					"host": [
						"localhost"
					],
					"port": "8080",
					"path": [
						"api",
						"timeformed",
						"meds"
					]
				}
			},
			"response": []
		},
		{
			"name": "http://localhost:8080/api/timeformed/meds",
			"request": {
				"auth": {
					"type": "noauth"
				},
				"method": "POST",
				"header": [],
				"body": {
					"mode": "raw",
					"raw": "{\r\n  \"name\": \"Paracetamol\",\r\n  \"description\": \"Para el dolor y fiebre\"\r\n}",
					"options": {
						"raw": {
							"language": "json"
						}
					}
				},
				"url": {
					"raw": "http://localhost:8080/api/timeformed/meds",
					"protocol": "http",
					"host": [
						"localhost"
					],
					"port": "8080",
					"path": [
						"api",
						"timeformed",
						"meds"
					]
				}
			},
			"response": []
		},
		{
			"name": "http://localhost:8080/api/timeformed/treatments",
			"request": {
				"method": "POST",
				"header": [],
				"body": {
					"mode": "raw",
					"raw": "{\r\n  \"name\": \"Tratamiento para la gripe\",\r\n  \"description\": \"Tratamiento intensivo durante 7 días\",\r\n  \"userId\": 2\r\n}",
					"options": {
						"raw": {
							"language": "json"
						}
					}
				},
				"url": {
					"raw": "http://localhost:8080/api/timeformed/treatments",
					"protocol": "http",
					"host": [
						"localhost"
					],
					"port": "8080",
					"path": [
						"api",
						"timeformed",
						"treatments"
					]
				}
			},
			"response": []
		},
		{
			"name": "http://localhost:8080/api/timeformed/meds/1",
			"request": {
				"auth": {
					"type": "noauth"
				},
				"method": "PUT",
				"header": [],
				"body": {
					"mode": "raw",
					"raw": "{\r\n  \"name\": \"Omeprazol\",\r\n  \"description\": \"Antiacido y antinflamatorio.\"\r\n}\r\n",
					"options": {
						"raw": {
							"language": "json"
						}
					}
				},
				"url": {
					"raw": "http://localhost:8080/api/timeformed/meds/1",
					"protocol": "http",
					"host": [
						"localhost"
					],
					"port": "8080",
					"path": [
						"api",
						"timeformed",
						"meds",
						"1"
					]
				}
			},
			"response": []
		},
		{
			"name": "http://localhost:8080/api/timeformed/meds/1",
			"protocolProfileBehavior": {
				"disableBodyPruning": true
			},
			"request": {
				"auth": {
					"type": "noauth"
				},
				"method": "GET",
				"header": [],
				"body": {
					"mode": "raw",
					"raw": "{\r\n  \"name\": \"Omeprazol\",\r\n  \"description\": \"Antiacido y antinflamatorio\"\r\n}\r\n"
				},
				"url": {
					"raw": "http://localhost:8080/api/timeformed/meds/1",
					"protocol": "http",
					"host": [
						"localhost"
					],
					"port": "8080",
					"path": [
						"api",
						"timeformed",
						"meds",
						"1"
					]
				}
			},
			"response": []
		},
		{
			"name": "http://localhost:8080/api/timeformed/meds",
			"protocolProfileBehavior": {
				"disableBodyPruning": true
			},
			"request": {
				"auth": {
					"type": "noauth"
				},
				"method": "GET",
				"header": [],
				"body": {
					"mode": "raw",
					"raw": "{\r\n  \"name\": \"Omeprazol\",\r\n  \"description\": \"Antiacido y antinflamatorio\"\r\n}\r\n"
				},
				"url": {
					"raw": "http://localhost:8080/api/timeformed/meds",
					"protocol": "http",
					"host": [
						"localhost"
					],
					"port": "8080",
					"path": [
						"api",
						"timeformed",
						"meds"
					]
				}
			},
			"response": []
		},
		{
			"name": "http://localhost:8080/api/timeformed/meds/1",
			"request": {
				"auth": {
					"type": "noauth"
				},
				"method": "DELETE",
				"header": [],
				"body": {
					"mode": "raw",
					"raw": "{\r\n  \"name\": \"Omeprazol\",\r\n  \"description\": \"Antiacido y antinflamatorio\"\r\n}\r\n"
				},
				"url": {
					"raw": "http://localhost:8080/api/timeformed/meds/1",
					"protocol": "http",
					"host": [
						"localhost"
					],
					"port": "8080",
					"path": [
						"api",
						"timeformed",
						"meds",
						"1"
					]
				}
			},
			"response": []
		},
		{
			"name": "http://localhost:8080/api/timeformed/treatments",
			"request": {
				"auth": {
					"type": "noauth"
				},
				"method": "POST",
				"header": [],
				"body": {
					"mode": "raw",
					"raw": "{\r\n  \"name\": \"Tratamiento para la gripe\",\r\n  \"description\": \"Tratamiento intensivo durante 7 días\",\r\n  \"userId\": 2\r\n}\r\n",
					"options": {
						"raw": {
							"language": "json"
						}
					}
				},
				"url": {
					"raw": "http://localhost:8080/api/timeformed/treatments",
					"protocol": "http",
					"host": [
						"localhost"
					],
					"port": "8080",
					"path": [
						"api",
						"timeformed",
						"treatments"
					]
				}
			},
			"response": []
		},
		{
			"name": "http://localhost:8080/api/timeformed/treatments",
			"request": {
				"method": "POST",
				"header": [],
				"body": {
					"mode": "raw",
					"raw": "{\r\n  \"name\": \"Tratamiento para la gripe\",\r\n  \"description\": \"Tratamiento intensivo durante 7 días\",\r\n  \"userId\": 2\r\n}\r\n",
					"options": {
						"raw": {
							"language": "json"
						}
					}
				},
				"url": {
					"raw": "http://localhost:8080/api/timeformed/treatments",
					"protocol": "http",
					"host": [
						"localhost"
					],
					"port": "8080",
					"path": [
						"api",
						"timeformed",
						"treatments"
					]
				}
			},
			"response": []
		},
		{
			"name": "http://localhost:8080/api/timeformed/treatments/2",
			"request": {
				"auth": {
					"type": "noauth"
				},
				"method": "PUT",
				"header": [],
				"body": {
					"mode": "raw",
					"raw": "{\r\n  \"name\": \"Tratamiento para la vista\",\r\n  \"description\": \"Tratamiento intensivo para 10 días\",\r\n  \"userId\": 2\r\n}\r\n",
					"options": {
						"raw": {
							"language": "json"
						}
					}
				},
				"url": {
					"raw": "http://localhost:8080/api/timeformed/treatments/1",
					"protocol": "http",
					"host": [
						"localhost"
					],
					"port": "8080",
					"path": [
						"api",
						"timeformed",
						"treatments",
						"1"
					]
				}
			},
			"response": []
		},
		{
			"name": "http://localhost:8080/api/timeformed/treatments/2",
			"protocolProfileBehavior": {
				"disableBodyPruning": true
			},
			"request": {
				"auth": {
					"type": "noauth"
				},
				"method": "GET",
				"header": [],
				"body": {
					"mode": "raw",
					"raw": "{\r\n  \"name\": \"Tratamiento para la gripe\",\r\n  \"description\": \"Tratamiento intensivo durante 10 días\",\r\n  \"userId\": 2\r\n}\r\n"
				},
				"url": {
					"raw": "http://localhost:8080/api/timeformed/treatments/1",
					"protocol": "http",
					"host": [
						"localhost"
					],
					"port": "8080",
					"path": [
						"api",
						"timeformed",
						"treatments",
						"1"
					]
				}
			},
			"response": []
		},
		{
			"name": "http://localhost:8080/api/timeformed/treatments",
			"protocolProfileBehavior": {
				"disableBodyPruning": true
			},
			"request": {
				"auth": {
					"type": "noauth"
				},
				"method": "GET",
				"header": [],
				"body": {
					"mode": "raw",
					"raw": "{\r\n  \"name\": \"Tratamiento para la gripe\",\r\n  \"description\": \"Tratamiento intensivo durante 10 días\",\r\n  \"userId\": 2\r\n}\r\n"
				},
				"url": {
					"raw": "http://localhost:8080/api/timeformed/treatments",
					"protocol": "http",
					"host": [
						"localhost"
					],
					"port": "8080",
					"path": [
						"api",
						"timeformed",
						"treatments"
					]
				}
			},
			"response": []
		},
		{
			"name": "http://localhost:8080/api/timeformed/treatments/2",
			"request": {
				"auth": {
					"type": "noauth"
				},
				"method": "DELETE",
				"header": [],
				"body": {
					"mode": "raw",
					"raw": "{\r\n  \"name\": \"Tratamiento para la gripe\",\r\n  \"description\": \"Tratamiento intensivo durante 10 días\",\r\n  \"userId\": 2\r\n}\r\n"
				},
				"url": {
					"raw": "http://localhost:8080/api/timeformed/treatments/1",
					"protocol": "http",
					"host": [
						"localhost"
					],
					"port": "8080",
					"path": [
						"api",
						"timeformed",
						"treatments",
						"1"
					]
				}
			},
			"response": []
		},
		{
			"name": "http://localhost:8080/api/timeformed/treatment-meds",
			"request": {
				"auth": {
					"type": "noauth"
				},
				"method": "POST",
				"header": [],
				"body": {
					"mode": "raw",
					"raw": "{\r\n  \"treatmentId\": 2,\r\n  \"medId\": 2,\r\n  \"dose\": \"500mg\",\r\n  \"frequencyHours\": 8,\r\n  \"durationDays\": 5,\r\n  \"startHour\": \"08:00\"\r\n}\r\n\r\n",
					"options": {
						"raw": {
							"language": "json"
						}
					}
				},
				"url": {
					"raw": "http://localhost:8080/api/timeformed/treatment-meds",
					"protocol": "http",
					"host": [
						"localhost"
					],
					"port": "8080",
					"path": [
						"api",
						"timeformed",
						"treatment-meds"
					]
				}
			},
			"response": []
		},
		{
			"name": "http://localhost:8080/api/timeformed/treatment-meds",
			"request": {
				"auth": {
					"type": "noauth"
				},
				"method": "POST",
				"header": [],
				"body": {
					"mode": "raw",
					"raw": "{\r\n  \"treatmentId\": 3,\r\n  \"medId\": 2,\r\n  \"dose\": \"700mg\",\r\n  \"frequencyHours\": 6,\r\n  \"durationDays\": 10,\r\n  \"startHour\": \"08:00\"\r\n}\r\n\r\n",
					"options": {
						"raw": {
							"language": "json"
						}
					}
				},
				"url": {
					"raw": "http://localhost:8080/api/timeformed/treatment-meds",
					"protocol": "http",
					"host": [
						"localhost"
					],
					"port": "8080",
					"path": [
						"api",
						"timeformed",
						"treatment-meds"
					]
				}
			},
			"response": []
		},
		{
			"name": "http://localhost:8080/api/timeformed/treatment-meds/1",
			"request": {
				"auth": {
					"type": "noauth"
				},
				"method": "PUT",
				"header": [],
				"body": {
					"mode": "raw",
					"raw": "{\r\n  \"treatmentId\": 2,\r\n  \"medId\": 2,\r\n  \"dose\": \"700mg\",\r\n  \"frequencyHours\": 8,\r\n  \"durationDays\": 9,\r\n  \"startHour\": \"08:00\"\r\n}\r\n\r\n",
					"options": {
						"raw": {
							"language": "json"
						}
					}
				},
				"url": {
					"raw": "http://localhost:8080/api/timeformed/treatment-meds/1",
					"protocol": "http",
					"host": [
						"localhost"
					],
					"port": "8080",
					"path": [
						"api",
						"timeformed",
						"treatment-meds",
						"1"
					]
				}
			},
			"response": []
		},
		{
			"name": "http://localhost:8080/api/timeformed/treatment-meds/1",
			"protocolProfileBehavior": {
				"disableBodyPruning": true
			},
			"request": {
				"auth": {
					"type": "noauth"
				},
				"method": "GET",
				"header": [],
				"body": {
					"mode": "raw",
					"raw": "{\r\n  \"treatmentId\": 1,\r\n  \"medId\": 2,\r\n  \"dose\": \"700mg\",\r\n  \"frequencyHours\": 8,\r\n  \"durationDays\": 9,\r\n  \"startHour\": \"08:00\"\r\n}\r\n\r\n"
				},
				"url": {
					"raw": "http://localhost:8080/api/timeformed/treatment-meds/1",
					"protocol": "http",
					"host": [
						"localhost"
					],
					"port": "8080",
					"path": [
						"api",
						"timeformed",
						"treatment-meds",
						"1"
					]
				}
			},
			"response": []
		},
		{
			"name": "http://localhost:8080/api/timeformed/treatment-meds",
			"protocolProfileBehavior": {
				"disableBodyPruning": true
			},
			"request": {
				"auth": {
					"type": "noauth"
				},
				"method": "GET",
				"header": [],
				"body": {
					"mode": "raw",
					"raw": "{\r\n  \"treatmentId\": 3,\r\n  \"medId\": 2,\r\n  \"dose\": \"700mg\",\r\n  \"frequencyHours\": 6,\r\n  \"durationDays\": 10,\r\n  \"startHour\": \"08:00\"\r\n}\r\n\r\n"
				},
				"url": {
					"raw": "http://localhost:8080/api/timeformed/treatment-meds",
					"protocol": "http",
					"host": [
						"localhost"
					],
					"port": "8080",
					"path": [
						"api",
						"timeformed",
						"treatment-meds"
					]
				}
			},
			"response": []
		},
		{
			"name": "http://localhost:8080/api/timeformed/treatment-meds/1",
			"request": {
				"auth": {
					"type": "noauth"
				},
				"method": "DELETE",
				"header": [],
				"body": {
					"mode": "raw",
					"raw": "{\r\n  \"treatmentId\": 1,\r\n  \"medId\": 2,\r\n  \"dose\": \"700mg\",\r\n  \"frequencyHours\": 8,\r\n  \"durationDays\": 9,\r\n  \"startHour\": \"08:00\"\r\n}\r\n\r\n"
				},
				"url": {
					"raw": "http://localhost:8080/api/timeformed/treatment-meds/1",
					"protocol": "http",
					"host": [
						"localhost"
					],
					"port": "8080",
					"path": [
						"api",
						"timeformed",
						"treatment-meds",
						"1"
					]
				}
			},
			"response": []
		},
		{
			"name": "http://localhost:8080/api/timeformed/takes",
			"request": {
				"auth": {
					"type": "noauth"
				},
				"method": "POST",
				"header": [],
				"body": {
					"mode": "raw",
					"raw": "{\r\n  \"treatmentMedId\": 2,\r\n  \"scheduledDateTime\": \"2025-06-17T08:00:00\",\r\n  \"takenDateTime\": \"2025-06-17T08:02:00\",\r\n  \"wasTaken\": true\r\n}\r\n",
					"options": {
						"raw": {
							"language": "json"
						}
					}
				},
				"url": {
					"raw": "http://localhost:8080/api/timeformed/takes",
					"protocol": "http",
					"host": [
						"localhost"
					],
					"port": "8080",
					"path": [
						"api",
						"timeformed",
						"takes"
					]
				}
			},
			"response": []
		},
		{
			"name": "http://localhost:8080/api/timeformed/takes/1",
			"request": {
				"auth": {
					"type": "noauth"
				},
				"method": "PUT",
				"header": [],
				"body": {
					"mode": "raw",
					"raw": "{\r\n  \"treatmentMedId\": 2,\r\n  \"scheduledDateTime\": \"2025-06-17T08:00:00\",\r\n  \"takenDateTime\": \"2025-06-17T08:02:00\",\r\n  \"wasTaken\": false\r\n}\r\n",
					"options": {
						"raw": {
							"language": "json"
						}
					}
				},
				"url": {
					"raw": "http://localhost:8080/api/timeformed/takes/1",
					"protocol": "http",
					"host": [
						"localhost"
					],
					"port": "8080",
					"path": [
						"api",
						"timeformed",
						"takes",
						"1"
					]
				}
			},
			"response": []
		},
		{
			"name": "http://localhost:8080/api/timeformed/takes/1",
			"protocolProfileBehavior": {
				"disableBodyPruning": true
			},
			"request": {
				"auth": {
					"type": "noauth"
				},
				"method": "GET",
				"header": [],
				"body": {
					"mode": "raw",
					"raw": "{\r\n  \"treatmentMedId\": 2,\r\n  \"scheduledDateTime\": \"2025-06-17T08:00:00\",\r\n  \"takenDateTime\": \"2025-06-17T08:02:00\",\r\n  \"wasTaken\": false\r\n}\r\n"
				},
				"url": {
					"raw": "http://localhost:8080/api/timeformed/takes/1",
					"protocol": "http",
					"host": [
						"localhost"
					],
					"port": "8080",
					"path": [
						"api",
						"timeformed",
						"takes",
						"1"
					]
				}
			},
			"response": []
		},
		{
			"name": "http://localhost:8080/api/timeformed/takes",
			"protocolProfileBehavior": {
				"disableBodyPruning": true
			},
			"request": {
				"auth": {
					"type": "noauth"
				},
				"method": "GET",
				"header": [],
				"body": {
					"mode": "raw",
					"raw": "{\r\n  \"treatmentMedId\": 2,\r\n  \"scheduledDateTime\": \"2025-06-17T08:00:00\",\r\n  \"takenDateTime\": \"2025-06-17T08:02:00\",\r\n  \"wasTaken\": false\r\n}\r\n"
				},
				"url": {
					"raw": "http://localhost:8080/api/timeformed/takes",
					"protocol": "http",
					"host": [
						"localhost"
					],
					"port": "8080",
					"path": [
						"api",
						"timeformed",
						"takes"
					]
				}
			},
			"response": []
		},
		{
			"name": "http://localhost:8080/api/timeformed/takes/1",
			"request": {
				"auth": {
					"type": "noauth"
				},
				"method": "DELETE",
				"header": [],
				"body": {
					"mode": "raw",
					"raw": "{\r\n  \"treatmentMedId\": 2,\r\n  \"scheduledDateTime\": \"2025-06-17T08:00:00\",\r\n  \"takenDateTime\": \"2025-06-17T08:02:00\",\r\n  \"wasTaken\": false\r\n}\r\n"
				},
				"url": {
					"raw": "http://localhost:8080/api/timeformed/takes/1",
					"protocol": "http",
					"host": [
						"localhost"
					],
					"port": "8080",
					"path": [
						"api",
						"timeformed",
						"takes",
						"1"
					]
				}
			},
			"response": []
		}
	]
}